dual_pairs/__init__.py
dual_pairs/abelian_group_homomorphism.py
dual_pairs/abelian_sheaf.py
dual_pairs/class_group.py
dual_pairs/dual_pair.py
dual_pairs/dual_pair_from_dihedral_field.py
dual_pairs/dual_pair_from_table.py
dual_pairs/dual_pair_import.py
dual_pairs/dual_pair_rational.py
dual_pairs/etale_algebra.py
dual_pairs/etale_algebras.py
dual_pairs/ext_group.py
dual_pairs/extension.py
dual_pairs/finite_flat_algebra.py
dual_pairs/finite_flat_algebra_element.py
dual_pairs/finite_flat_algebra_module.py
dual_pairs/group_structure.py
dual_pairs/padic_roots.py
dual_pairs/padic_splitting_field.py
dual_pairs/selmer_group.py
dual_pairs/simplicial_sheaf.py
dual_pairs/smith_form.py
dual_pairs/torsor_class_group.py
dual_pairs/torsor_pair.py
dual_pairs/unit_group.py
dual_pairs/example_data/D4_mod_3.gp
dual_pairs/example_data/GL2_mod_3.gp
dual_pairs/example_data/GL2_mod_5.gp
dual_pairs/example_data/GL2_mod_7.gp
dual_pairs-0.5.dist-info/COPYING
dual_pairs-0.5.dist-info/METADATA
dual_pairs-0.5.dist-info/WHEEL
dual_pairs-0.5.dist-info/top_level.txt
dual_pairs-0.5.dist-info/RECORD
