Metadata-Version: 2.1
Name: dual-pairs
Version: 0.5
Summary: SageMath package for computing with dual pairs of algebras
Home-page: https://gitlab.com/pbruin/dual-pairs
Author: Peter Bruin
Author-email: P.J.Bruin@math.leidenuniv.nl
Classifier: Topic :: Scientific/Engineering :: Mathematics
Classifier: Intended Audience :: Science/Research
Classifier: Programming Language :: Python
Classifier: Operating System :: OS Independent
Classifier: Development Status :: 3 - Alpha
Classifier: License :: OSI Approved :: GNU General Public License v3 or later (GPLv3+)
License-File: COPYING
Requires-Dist: sagemath
Provides-Extra: doc
Requires-Dist: sphinx (>=2) ; extra == 'doc'
